Metadata-Version: 2.1
Name: ccxmeshreader
Version: 0.2.0
Summary: Reads a mesh from CalcluliX input (.inp) files.
Home-page: https://github.com/gbroques/ccxmeshreader
Author: G Roques
License: UNKNOWN
Platform: UNKNOWN
Classifier: License :: OSI Approved :: GNU Lesser General Public License v2 or later (LGPLv2+)
Classifier: Programming Language :: Python :: 3 :: Only
